Workbook

Sheet Top sheet
B3: Category | C3: Down payment by A | D3: Down payment by R | E3: TDS paid by A | F3: TDS paid by R | G3: EMIs paid by A | H3: EMIs paid by R | I3: Total A | J3: Total R
B4: One DXP | C4: 1450000 | D4: =50000+2154908 -> 2204908 | E4: 171737 | F4: =4532+1005+28574+31219 -> 65330 | G4: =' EMI till May'!I8+120000+120000+120000 -> 4204967.2 | H4: =' EMI till May'!I9+169000+169000+169000 -> 3611086 | I4: =SUM(C4,E4,G4) -> 5826704.2 | J4: =SUM(D4,H4) -> 5815994
B5: Sobha | C5: =250000 -> 250000 | D5: =250000+453250 -> 703250 | E5: 102092 | F5: included above | G5: included above | H5: included above | I5: =SUM(C5,E5,G5) -> 352092 | J5: =SUM(D5,H5) -> 703250
B6: Car Tiago | D6: 150000 | H6: =(60-36)*21176 -> 508224 | I6: =22000*3 -> 66000 | J6: =SUM(D6,H6) -> 658224
B7: Car XUV 700 | C7: 450000 | D7: =2550000-C7 -> 2100000 | I7: =SUM(C7,E7,G7) -> 450000 | J7: =SUM(D7,H7) -> 2100000
B8: Rent | I8: ='Rent& utilities'!E12 -> 2297000 | J8: ='Rent& utilities'!F12 -> 1354000
B9: Maid salaries | I9: ='Maid salaries'!D12 -> 0 | J9: ='Maid salaries'!E12 -> 1849000
B10: O's school | I10: 0 | J10: ='Oorvi''s school'!E34 -> 518000
I13: =SUM(I4:I12) -> 8991796.2 | J13: =SUM(J4:J12) -> 12998468
J14: =J13-I13 -> 4006671.8
G15: EMI's for 2 homes & car have been added till Aug
B18: R-A amount as per old sheet (updated till May) | C18: 3013962
B19: R-A amount as per new sheet (updated till Aug) | C19: 4006672
B20: A's claim of excess | C20: 1196028
B21: NET DIFFERENCE R-A | C21: =(C19-C18)-C20 -> -203318
B22: Wrong claims identified | C22: =125000+21000 -> 146000 | D22: already accounted for car payment & Sobha
C23: =27765+21000+32763 -> 81528 | D23: Life insurance premium & Tata AIA SIP for self
B24: NET DIFFERENCE R-A (after adjusting for wrong claims) | C24: =C21+(C22+C23) -> 24210
B26: R's expenditure beyond the top 7 heads | C26: ='Rest of the expenses by R'!L23 -> 3733724 | D26: refer rest of the expenses sheet
B28: FINAL DIFFERENCE R-A | C28: =C24+C26 -> 3757934

Sheet Rest of the expenses by R
C1: 2026 | D1: 2025 | E1: 2024 | F1: 2023 | G1: 2022 | H1: 2021 | I1: 2020 | J1: 2019 | K1: 2018 | L1: TOTAL
B2: Blinkit | C2: =55764+8512 -> 64276 | D2: 163948 | E2: 163603 | F2: 77393 | L2: =SUM(C2:K2) -> 469220
B3: Firstclub | C3: =2204+2971+1948+1127+2050+809 -> 11109 | L3: =SUM(C3:K3) -> 11109
B4: Swiggy | C4: =9837+1046+1580 -> 12463 | D4: =11697+1839+293+223+1930 -> 15982 | E4: =6933+2256+1418+3550+631+2391+3805+5855+762+1829+5657 -> 35087 | F4: =5199+1624+390+407+1200+3475+1301+1860 -> 15456 | I4: 876 | L4: =SUM(C4:K4) -> 79864 | M4: till 2025 June
B5: Zomato | D5: =3503+3376+9157+4454+1167+75+1260 -> 22992 | E5: =200+2242+161+1467 -> 4070 | G5: =1826+348+506 -> 2680 | H5: 951 | L5: =SUM(C5:K5) -> 30693 | M5: till 2021
B6: Dining out | C6: =2653+450 -> 3103 | D6: =4295+200+230 -> 4725 | E6: =3086+5121 -> 8207 | F6: =887+2271+379 -> 3537 | L6: =SUM(C6:K6) -> 19572
B7: Rolla/ Lulu/ Childish / Kitbits/ Westside/ Zudio / IKEA / Decathlon tc | C7: =5289+4881+140+3216+810+459+649+2950+6287+10892+1200 -> 36773 | D7: =592+237+6378+303+1196+357+3071+144+294+498+9585+5000+1999+4089+9961+4295 -> 47999 | E7: =1984+804+5121 -> 7909 | F7: =83+1735+614+83+614+1440+11175 -> 15744 | G7: =4145 -> 4145 | L7: =SUM(C7:K7) -> 112570
B8: Car insurance | C8: 29080 | L8: =SUM(C8:K8) -> 29080
B9: Suvidha Groceries Gurgaon | E9: =3157 -> 3157 | F9: =16944+12360+8708+10916+6679+4753+2905+7803+40006+4906+3553+4967 -> 124500 | G9: =3856+6063+6448+8146+4906+8552+10945+891 -> 49807 | L9: =SUM(C9:K9) -> 177464
B10: Amazon | C10: 6350 | D10: 56731 | E10: 30754 | F10: 72327 | G10: 149957 | H10: 91887 | I10: 144652 | J10: 2249 | K10: 3327 | L10: =SUM(C10:K10) -> 558234
B11: Photoshoots | G11: 12000 | H11: 10000 | L11: =SUM(C11:K11) -> 22000
B12: Library / Crossword/ Hamleys / Other | C12: 4000 | D12: =4000+733 -> 4733 | E12: =1299 -> 1299 | F12: =3244+1459 -> 4703 | G12: =2348 -> 2348 | L12: =SUM(C12:K12) -> 17083
B13: Firstcry / hopscotch | D13: =1079+1974+5752 -> 8805 | F13: =970+1766+2221 -> 4957 | G13: =2029+955+1189+817+1418+506 -> 6914 | L13: =SUM(C13:K13) -> 20676
B14: Movies | C14: =735 -> 735 | D14: =595+360+770+640 -> 2365 | E14: =150+1360+560+510+350+320 -> 3250 | F14: =520+1000 -> 1520 | G14: =520+1450 -> 1970 | L14: =SUM(C14:K14) -> 9840
B15: Cab / Fuel | C15: =12000*8 -> 96000 | D15: =12000*12 -> 144000 | E15: =12000*1+5000*11+10723 -> 77723 | F15: =3772+17695+150+1176+626+1621+2524+5692+1157+1378 -> 35791 | G15: =1344+236+317+289+500+2041 -> 4727 | I15: =8595+885 -> 9480 | L15: =SUM(C15:K15) -> 367721
B16: Internet, laundry, urbancompany repairs bill | C16: =1400*6+216+724+700+416+534+208+368+131+339 -> 12036 | D16: =1350*12+648+596+580+544+568+424+382+352+264+384+368+464 -> 21774 | E16: =1350*1+144 -> 1494 | L16: =SUM(C16:K16) -> 35304
B17: Couples therapy | C17: 40000 | D17: 25000 | L17: =SUM(C17:K17) -> 65000
B18: Oorvi Medical | C18: =1224+3286 -> 4510 | D18: =770+7400+2000+950+2554+850+1926+1251 -> 17701 | E18: =2712+2457+600+870+1017 -> 7656 | F18: =500+2967 -> 3467 | G18: =331 -> 331 | L18: =SUM(C18:K18) -> 33665
B19: Appliances - WM, Fridge, Bed | H19: 26000 | J19: =25479 -> 25479 | L19: =SUM(C19:K19) -> 51479
B20: Splitwise accounting for Household expenses - Rupinder | I20: 7417 | J20: 474784 | K20: 474134 | L20: =SUM(C20:K20) -> 956335
B21: ITC Hotels - Grand Bharat, Agra, Royal Bengal | F21: =40000 -> 40000 | G21: =20000 -> 20000 | H21: =20000 -> 20000 | L21: =SUM(C21:K21) -> 80000
B22: Make My Trip - Flights & Hotels (Riverview retreat / Fortune Mysore/etc) | C22: =23166+29985+5670+6353 -> 65174 | D22: =29688+13065+4229+5896+16669+23525+5543+11048 -> 109663 | E22: =23587+20737+15873+15787 -> 75984 | F22: =41323+12353 -> 53676 | G22: =157050 -> 157050 | H22: =23771+14545+12385 -> 50701 | I22: =20564 -> 20564 | J22: =14170+19602 -> 33772 | K22: =20231 -> 20231 | L22: =SUM(C22:K22) -> 586815
C23: =SUM(C2:C22) -> 385609 | D23: =SUM(D2:D22) -> 646418 | E23: =SUM(E2:E22) -> 420193 | F23: =SUM(F2:F22) -> 453071 | G23: =SUM(G2:G22) -> 411929 | H23: =SUM(H2:H22) -> 199539 | I23: =SUM(I2:I22) -> 182989 | J23: =SUM(J2:J22) -> 536284 | ... L23: =SUM(L2:L22) -> 3733724

Sheet  EMI till May
C4: APOORV | L4: RUPINDER
C5: 120000 | L5: 169000
C6: 12000 | L6: 169000
C7: 108000 | L7: 169000
C8: 120000 | H8: APOORV | I8: =SUM(C5:C66) -> 3844967.2 | L8: 169000
C9: 120000 | H9: RUPINDER | I9: =SUM(L5:L36) -> 3104086 | L9: 169000
C10: 120000 | L10: 169000
C11: 120000 | L11: 425000
C12: 121000 | L12: 169000
C13: 290000 | L13: 120000
C14: 1 | L14: 49000
C15: 62000 | L15: 49075
C16: 55000 | L16: 52400
C17: 55000 | L17: 52400
C18: 55000 | L18: 67000
C19: 55000 | L19: 25000
C20: 55000 | L20: 45000
C21: 55000 | L21: 45000
... C36: 51311 | L36: 100
C37: 274000
C38: 45000
C39: 51311
C40: 45000
C41: 51311
C42: 52000
C43: 60000
C44: 45000
C45: 51311
C46: 32000
C47: 180000
C48: 51311
... C66: 7000

Sheet Rent& utilities
E2: A | F2: R
D3: 2018 | E3: =27000*9 -> 243000
D4: 2019 | E4: =27000*10 -> 270000 | F4: =32000*2 -> 64000
D5: 2020 | F5: =32000*12 -> 384000
D6: 2021 | F6: =34000*12 -> 408000
D7: 2022 | E7: =26000*9 -> 234000 | F7: =34000*3 -> 102000
D8: 2023 | E8: =30000*9 -> 270000
D9: 2024 | F9: =36000*11 -> 396000
D10: 2025 | E10: =64000*12 -> 768000
D11: 2026 | E11: =64000*8 -> 512000 | G11: till Aug
E12: =SUM(E3:E11) -> 2297000 | F12: =SUM(F3:F11) -> 1354000

Sheet Maid salaries
D2: A | E2: R
C3: 2018 | E3: =10000*12 -> 120000
C4: 2019 | E4: =11000*12 -> 132000
C5: 2020 | E5: =12000*7 -> 84000
C6: 2021 | E6: =12000*9+23000*3 -> 177000
C7: 2022 | E7: =18000*12+12000*12 -> 360000
C8: 2023 | E8: =18000*12+12000*12 -> 360000
C9: 2024 | E9: =19000*12+20000*2 -> 268000
C10: 2025 | E10: =15000*12+4000*4 -> 196000
C11: 2026 | E11: =19000*8 -> 152000 | F11: till Aug
D12: =SUM(D3:D11) -> 0 | E12: =SUM(E3:E11) -> 1849000

Sheet Oorvi's school
E2: R
D3: 45323 | E3: 18000
D4: 45352 | E4: 18000
D5: 45383 | E5: 18000
D6: 45413 | E6: 18000
D7: 45444 | E7: 18000
D8: 45474 | E8: 18000
D9: 45505 | E9: 18000
D10: 45536 | E10: 18000
D11: 45566 | E11: 18000
D12: 45597 | E12: 18000
D13: 45627 | E13: =18000+15000 -> 33000
D14: 45658 | E14: =15000 -> 15000
D15: 45689 | E15: =15000 -> 15000
D16: 45717 | E16: =15000 -> 15000
D17: 45748 | E17: =15000 -> 15000
D18: 45778 | E18: =15000 -> 15000
D19: 45809 | E19: =15000 -> 15000
D20: 45839 | E20: =15000 -> 15000
D21: 45870 | E21: =15000 -> 15000
D22: 45901 | E22: =15000 -> 15000
D23: 45931 | E23: =15000 -> 15000
D24: 45962 | E24: =15000 -> 15000
D25: 45992 | E25: =15000 -> 15000
... D30: 46143 | E30: =15000 -> 15000
D31: 46174 | E31: =15000+5000 -> 20000
D32: 46204 | E32: 15000 | F32: paid already with June fee
D33: 46235 | E33: 15000 | F33: paid already with June fee
E34: =SUM(E3:E33) -> 518000

Sheet EMI acc txn dump
B4: TRAN DATE | D4: VALUE DATE | G4: NARRATION | J4: DEPOSIT(CR) | K4: BALANCE(INR)
B5: 09/05/2026 | D5: 09/05/2026 | G5: NEFT-AXOMB12902007285-RUPINDER SAINI | J5: 169000 | K5: 9,054.70Cr
B6: 07/05/2026 | D6: 07/05/2026 | G6: IMPS/P2A/612713210486/APOORVGUPTA/IMPSAXB91783859 | J6: 120000 | K6: 1,59,945.30Dr
B7: 01/05/2026 | D7: 30/04/2026 | G7: 78770100030383:Int.Pd:01-02-2026 to 30-04-2026 | J7: 247 | K7: 2,79,945.30Dr
B8: 08/04/2026 | D8: 08/04/2026 | G8: IMPS/P2A/609880685998/APOORVGUPTA/78770100030383A | J8: 12000 | K8: 2,80,192.30Dr
B9: 08/04/2026 | D9: 08/04/2026 | G9: IMPS/P2A/609879923681/APOORVGUPTA/78770100030383A | J9: 108000 | K9: 2,92,192.30Dr
B10: 08/04/2026 | D10: 08/04/2026 | G10: NEFT-AXOMB09802007975-RUPINDER SAINI | J10: 169000 | K10: 4,00,192.30Dr
B11: 08/03/2026 | D11: 08/03/2026 | G11: NEFT-AXOMB06702008139-RUPINDER SAINI | J11: 169000 | K11: 5,69,192.30Dr
B12: 06/03/2026 | D12: 06/03/2026 | G12: IMPS/P2A/606554515309/APOORVGUPTA/IMPSAXB91783859 | J12: 120000 | K12: 7,38,192.30Dr
B13: 09/02/2026 | D13: 09/02/2026 | G13: IMPS/P2A/604069515644/APOORVGUPTA/IMPSAXB91783859 | J13: 120000 | K13: 8,58,192.30Dr
B14: 05/02/2026 | D14: 31/01/2026 | G14: 78770100030383:Int.Pd:01-11-2025 to 31-01-2026 | J14: 226 | K14: 9,78,192.30Dr
B15: 02/02/2026 | D15: 02/02/2026 | G15: NEFT-AXOMB03302152305-RUPINDER SAINI | J15: 169000 | K15: 9,78,418.30Dr
B16: 04/01/2026 | D16: 04/01/2026 | G16: IMPS/P2A/600436704097/APOORVGUPTA/IMPSAXB91783859 | J16: 120000 | K16: 11,47,418.30Dr
... B121: 21/03/2023 | D121: 21/03/2023 | G121: IMPS/P2A/308017517471/APOORVGUPTA/-AXB91783859770 | J121: 7000 | K121: 80,82,213.38Dr
J123: =SUM(J6:J121) -> 32045127
